Sylvac/DataBase.py
Sylvac/__init__.py
Sylvac/icons_rc.py
Sylvac/main.py
Sylvac/ui_main.py
Sylvac-0.3.5.dist-info/METADATA
Sylvac-0.3.5.dist-info/WHEEL
Sylvac-0.3.5.dist-info/top_level.txt
Sylvac-0.3.5.dist-info/RECORD
