Metadata-Version: 2.1
Name: Sylvac
Version: 0.3.5
Summary: Phan mem doc thuoc
Home-page: https://github.com/huynhquoc1990/Sylvac.git
Author: quoc
Author-email: huynhquoc1990@gmail.com
License: MIT
Platform: UNKNOWN
Classifier: Programming Language :: Python :: 3
Classifier: License :: OSI Approved :: MIT License
Classifier: Operating System :: OS Independent
